STEMDIFF/__init__.py
STEMDIFF/__main__.py
STEMDIFF/dbase.py
STEMDIFF/detectors.py
STEMDIFF/gvars.py
STEMDIFF/io.py
STEMDIFF/sum.py
STEMDIFF/summ.py
stemdiff-5.2.11.dist-info/licenses/LICENCE
stemdiff-5.2.11.dist-info/METADATA
stemdiff-5.2.11.dist-info/WHEEL
stemdiff-5.2.11.dist-info/top_level.txt
stemdiff-5.2.11.dist-info/RECORD
