Metadata-Version: 2.4
Name: stemdiff
Version: 5.2.11
Summary: Convert 4D-STEM data to 2D-powder diffraction pattern.
Home-page: https://github.com/mirekslouf/stemdiff/
Author: Mirek Slouf
Author-email: mirek.slouf@gmail.com
License: MIT
Project-URL: Documentation, https://mirekslouf.github.io/stemdiff/
Classifier: Programming Language :: Python :: 3
Classifier: License :: OSI Approved :: MIT License
Classifier: Operating System :: OS Independent
Requires-Python: >=3.6
License-File: LICENCE
Requires-Dist: numpy
Requires-Dist: matplotlib
Requires-Dist: scipy
Requires-Dist: pandas
Requires-Dist: scikit-image
Dynamic: author
Dynamic: author-email
Dynamic: classifier
Dynamic: description
Dynamic: description-content-type
Dynamic: home-page
Dynamic: license
Dynamic: license-file
Dynamic: project-url
Dynamic: requires-dist
Dynamic: requires-python
Dynamic: summary
